my_package_vajain/__init__.py
my_package_vajain/example.py
my_package_vajain/first/__init__.py
my_package_vajain/first/first_level.py
my_package_vajain/second/__init__.py
my_package_vajain/second/second_level.py
my_package_vajain/third/__init__.py
my_package_vajain/third/third_level.py
my_package_vajain-0.0.1.dist-info/LICENSE.txt
my_package_vajain-0.0.1.dist-info/METADATA
my_package_vajain-0.0.1.dist-info/WHEEL
my_package_vajain-0.0.1.dist-info/top_level.txt
my_package_vajain-0.0.1.dist-info/RECORD
